pollen_api_dwd/__init__.py
pollen_api_dwd/client.py
pollen_api_dwd-0.1.9.dist-info/licenses/LICENSE
pollen_api_dwd-0.1.9.dist-info/METADATA
pollen_api_dwd-0.1.9.dist-info/WHEEL
pollen_api_dwd-0.1.9.dist-info/top_level.txt
pollen_api_dwd-0.1.9.dist-info/RECORD
