Metadata-Version: 2.4
Name: pollen_api_dwd
Version: 0.1.9
Summary: Async client for the DWD pollen forecast data API
Author-email: Sven Gerlach <pypi@rexkramer.de>
License: MIT License
Project-URL: Homepage, https://github.com/rexdek/pollen_api_dwd
Project-URL: Repository, https://github.com/rexdek/pollen_api_dwd.git
Requires-Python: >=3.9
License-File: LICENSE
Requires-Dist: aiohttp
Provides-Extra: test
Requires-Dist: pytest; extra == "test"
Requires-Dist: pytest-asyncio; extra == "test"
Requires-Dist: freezegun; extra == "test"
Dynamic: license-file
